edispatcher/__init__.py
edispatcher/edispatcher.py
tests/__init__.py
tests/test_event_dispatcher.py
edispatcher-0.1.1.dist-info/LICENSE
edispatcher-0.1.1.dist-info/METADATA
edispatcher-0.1.1.dist-info/WHEEL
edispatcher-0.1.1.dist-info/top_level.txt
edispatcher-0.1.1.dist-info/RECORD
