Metadata-Version: 2.1
Name: edispatcher
Version: 0.1.1
Summary: A simple event dispatcher implementation in Python
Home-page: https://github.com/dmtno/edispatcher
Author: dmtno
License: MIT
Classifier: Programming Language :: Python :: 3
Classifier: Programming Language :: Python :: 3.11
Classifier: License :: OSI Approved :: MIT License
Classifier: Operating System :: OS Independent
Requires-Python: >=3.11
License-File: LICENSE
